jsondb/__init__.py
jsondb/_lockfile_util.py
jsondb/database.py
jsondb_hakimifr-0.3.1.dist-info/METADATA
jsondb_hakimifr-0.3.1.dist-info/WHEEL
jsondb_hakimifr-0.3.1.dist-info/entry_points.txt
jsondb_hakimifr-0.3.1.dist-info/licenses/LICENSE
jsondb_hakimifr-0.3.1.dist-info/RECORD
