Metadata-Version: 2.4
Name: jsondb-hakimifr
Version: 0.3.1
Summary: Imagine using JSON as database. Wait... that's me!
Author-email: Firdaus Hakimi <hakimifirdaus944@gmail.com>
License: Apache-2.0
License-File: LICENSE
Requires-Python: >=3.12
